casdoor_auth/__init__.py
casdoor_auth/apps.py
casdoor_auth/tests.py
casdoor_auth/urls.py
casdoor_auth/user.py
casdoor_auth/views.py
django_casdoor_auth-1.1.0.dist-info/LICENSE
django_casdoor_auth-1.1.0.dist-info/METADATA
django_casdoor_auth-1.1.0.dist-info/WHEEL
django_casdoor_auth-1.1.0.dist-info/top_level.txt
django_casdoor_auth-1.1.0.dist-info/RECORD
