Metadata-Version: 2.1
Name: django-casdoor-auth
Version: 1.1.0
Summary: An app for use Casdoor SSO
Home-page: https://github.com/casdoor/django-auth-sso
Author: leo220yuyaodog
Author-email: magicwindyyd@gmail.com
License: Apache 2.0
Keywords: Casdoor Django
Platform: any
Classifier: Intended Audience :: Developers
Classifier: License :: OSI Approved :: Apache Software License
Classifier: Operating System :: OS Independent
Classifier: Programming Language :: Python
Classifier: Programming Language :: Python :: 3.6
Classifier: Programming Language :: Python :: 3.7
Classifier: Programming Language :: Python :: 3.8
Classifier: Programming Language :: Python :: 3.9
Classifier: Framework :: Django
Classifier: Framework :: Django :: 3.0
Classifier: Framework :: Django :: 3.1
Classifier: Framework :: Django :: 3.2
Classifier: Framework :: Django :: 4.0
Classifier: Framework :: Django :: 4.1
Requires-Python: >=3.6
License-File: LICENSE
Requires-Dist: django
Requires-Dist: casdoor
